main.py
convert_csv-0.2.3.dist-info/METADATA
convert_csv-0.2.3.dist-info/WHEEL
convert_csv-0.2.3.dist-info/entry_points.txt
convert_csv-0.2.3.dist-info/top_level.txt
convert_csv-0.2.3.dist-info/RECORD
