Metadata-Version: 2.4
Name: convert-csv
Version: 0.2.3
Summary: A simple and easy-to-use CSV format converter that helps you process amount and date formats in batch.
Requires-Python: >=3.8
Requires-Dist: chardet>=5.2.0
Requires-Dist: pandas>=2.3.2
